grpc_prometheus_metrics/__init__.py
grpc_prometheus_metrics/aio/__init__.py
grpc_prometheus_metrics/aio/prometheus_aio_client_interceptor.py
grpc_prometheus_metrics/aio/prometheus_aio_server_interceptor.py
grpc_prometheus_metrics/client_metrics.py
grpc_prometheus_metrics/grpc_utils.py
grpc_prometheus_metrics/prometheus_client_interceptor.py
grpc_prometheus_metrics/prometheus_server_interceptor.py
grpc_prometheus_metrics/server_metrics.py
grpc_prometheus_metrics-0.0.5.dist-info/LICENSE
grpc_prometheus_metrics-0.0.5.dist-info/METADATA
grpc_prometheus_metrics-0.0.5.dist-info/WHEEL
grpc_prometheus_metrics-0.0.5.dist-info/RECORD
