Metadata-Version: 2.1
Name: grpc-prometheus-metrics
Version: 0.0.5
Summary: Python gRPC Prometheus Interceptors, py-grpc-prometheus fork
License: Apache-2.0
Author: Sergio Soldatov
Author-email: soldatovsr97@gmail.com
Requires-Python: >=3.10,<4.0
Classifier: License :: OSI Approved :: Apache Software License
Classifier: Programming Language :: Python :: 3
Classifier: Programming Language :: Python :: 3.10
Classifier: Programming Language :: Python :: 3.11
Classifier: Programming Language :: Python :: 3.12
Requires-Dist: grpcio (>=1.10.0)
Requires-Dist: prometheus-client (>=0.3.0)
Requires-Dist: setuptools (>=39.0.1)
